<?xml version="1.0" encoding="utf-8"?>
<resources>
<!--    Les arrays utile dans l'application-->
    <string-array name="array_gender">
        <item>Maschile</item>
        <item>Femminile</item>
        <item>Altri</item>
    </string-array>

    <string-array name="array_language_international">
        <item>Inglese, EN</item>
        <item>Francese, FR</item>
        <item>Portoghese, PT</item>
        <item>Spagnolo, ES</item>
        <item>Arabo, AR</item>
        <item>Cinese, ZH</item>
        <item>Tedesco, DE</item>
        <item>Russo, RU</item>
        <item>Latino, LA</item>
    </string-array>
</resources>